[{"ImageID": 0, "Page": 2, "Type": "Figure", "Imagebbox": [0.09058823529411765, 0.600909090909091, 0.4788235294117647, 0.8445454545454546], "Caption": "Figure 2:", "DPI": 100, "CaptionBB": [215, 945, 261, 957], "first_confirmed": false, "second_confirmed": false}, {"ImageID": 1, "Page": 2, "Type": "Figure", "Imagebbox": [0.09058823529411765, 0.06636363636363636, 0.4788235294117647, 0.31363636363636366], "Caption": "Figure 1:", "DPI": 100, "CaptionBB": [215, 360, 261, 372], "first_confirmed": false, "second_confirmed": false}]