[{"ImageID": 0, "Page": 1, "Type": "Figure", "Imagebbox": [0.5694117647058824, 0.5418181818181819, 0.8611764705882353, 0.66], "Caption": "Figure 2: Left: Node x has a tree of ancestors (parents, grandparents, etc.) and a tree of descendants (children, grandchildren, etc.), both of which may be drawn with conventional tree-drawing techniques. Right: It is more challenging, however, to also show the descendants of y, or worse still, to show the descendants of every ancestor of x, and the ancestors of every descendant of x. Note: in this and other figures, squares represent males, circles females.", "DPI": 100, "CaptionBB": [440, 739, 775, 833], "first_confirmed": false, "second_confirmed": false}, {"ImageID": 1, "Page": 1, "Type": "Figure", "Imagebbox": [0.5152671755725191, 0.1855641592920354, 0.9247058823529412, 0.32181818181818184], "Caption": "Figure 1: Portion of a genealogical graph for an actual family, laid out manually, containing well over 600 individuals and spanning almost 400 years. (Sample data set supplied with GenoPro [7]).", "DPI": 100, "CaptionBB": [440, 370, 775, 409], "first_confirmed": false, "second_confirmed": false}, {"ImageID": 2, "Page": 2, "Type": "Figure", "Imagebbox": [0.5623529411764706, 0.1481818181818182, 0.8694117647058823, 0.25181818181818183], "Caption": "Figure 3: Left: an example multitree. Observe that the two trees of descendants rooted at nodes A and C, respectively, share two subtrees, rooted at nodes F and P, respectively. Right: Node M is highlighted, along with its tree of ancestors and tree of descendants.", "DPI": 100, "CaptionBB": [440, 292, 775, 345], "first_confirmed": false, "second_confirmed": false}, {"ImageID": 3, "Page": 3, "Type": "Figure", "Imagebbox": [0.5694117647058824, 0.06636363636363636, 0.8611764705882353, 0.14909090909090908], "Caption": "Figure 4: A: conventional notation for a nuclear family: squares are male, circles female, and children extend downward from an edge connecting the parents. B\u2013E show different ways of modelling such a family within a directed graph. B: the \u2295 symbol denotes a \u201cspousal union\u201d node. C: alternative scheme that avoids any special, inter- mediate node, but requires more edges when there are 3 or more children. D: Nelson\u2019s scheme for encoding families within zzstruc- tures. Each child links to its next older sibling, and the eldest child links to the \u201cspousal union\u201d node. E: a variation on D that prevents cycles in the directed graph.", "DPI": 100, "CaptionBB": [440, 179, 775, 310], "first_confirmed": false, "second_confirmed": false}, {"ImageID": 4, "Page": 3, "Type": "Figure", "Imagebbox": [0.5905882352941176, 0.39545454545454545, 0.8411764705882353, 0.5154545454545455], "Caption": "Figure 5: Example situation where a long edge cannot be avoided, even if some branches are rotated. Also, the vertical ordering of nodes by generation is broken: it is not immediately apparent that nodes x and y are of the same generation \u2014 they are 3rd cousins. The ordering by generation could be restored by introducing edge- crossings, but at least one edge would still be long.", "DPI": 100, "CaptionBB": [440, 583, 775, 662], "first_confirmed": false, "second_confirmed": false}, {"ImageID": 5, "Page": 4, "Type": "Figure", "Imagebbox": [0.5729411764705883, 0.5772727272727273, 0.8564705882352941, 0.67], "Caption": "Figure 8: Different graphical representations of the same rooted tree. A: node-link. B: nested containment, or enclosure. C: a layered \u201cicicle\u201d diagram, that uses adjacency and alignment to imply the tree structure. D: an indented outline view.", "DPI": 100, "CaptionBB": [440, 754, 775, 806], "first_confirmed": false, "second_confirmed": false}, {"ImageID": 6, "Page": 4, "Type": "Figure", "Imagebbox": [0.6317647058823529, 0.13545454545454547, 0.8, 0.26636363636363636], "Caption": "Figure 7: A fractal layout for G\u2217 , showing the same 9 nuclear families as in Figure 6, along with some additional nodes in grey.", "DPI": 100, "CaptionBB": [440, 306, 775, 334], "first_confirmed": false, "second_confirmed": false}, {"ImageID": 7, "Page": 4, "Type": "Figure", "Imagebbox": [0.08705882352941176, 0.2736363636363636, 0.49411764705882355, 0.39454545454545453], "Caption": "Figure 6: A portion of an idealized genealogical graph, G\u2217 . Nine nuclear families are shown (each outlined in pink), labelled n 0 , . . . , n8 . Ellipses indicate the many directions in which this diagram could be extended, suggesting that nodes would rapidly become crowded.", "DPI": 100, "CaptionBB": [73, 448, 408, 502], "first_confirmed": false, "second_confirmed": false}, {"ImageID": 8, "Page": 5, "Type": "Figure", "Imagebbox": [0.52, 0.22181818181818183, 0.9247058823529412, 0.3572727272727273], "Caption": "Figure 10: Combinations of canonical subsets of genealogical graphs. A: The tree A(x) of ancestors and tree D(x) of descendants of x form an hourglass diagram. B: This dual-tree scheme shows more information, by showing D(y) \u2283 D(x). C: An example dual-tree.", "DPI": 100, "CaptionBB": [440, 410, 775, 463], "first_confirmed": false, "second_confirmed": false}, {"ImageID": 9, "Page": 5, "Type": "Figure", "Imagebbox": [0.08705882352941176, 0.2736363636363636, 0.4929411764705882, 0.5781818181818181], "Caption": "Figure 9: A free tree can be drawn using the nested containment style of Figure 8, B, if the user\u2019s current \u201cfocus\u201d is used as a temporary root. Top: a genealogical graph, drawn using conventional notation. For simplicity, squares are used for all individuals, not just males. Lower left: the same graph, drawn using nested containment, with the nuclear family {F, I, O, P} as the root. This is analogous to the representation in Figure 7, with larger nodes containing smaller nodes rather than being connected to them with line segments. Lower right: now, the nuclear family {P, R,U,V,W } is the root.", "DPI": 100, "CaptionBB": [73, 651, 408, 769], "first_confirmed": false, "second_confirmed": false}, {"ImageID": 10, "Page": 6, "Type": "Figure", "Imagebbox": [0.52, 0.4290909090909091, 0.9223529411764706, 0.6790909090909091], "Caption": "Figure 12: A dual-tree laid out 3 different ways by the prototype. Nodes are coloured by gender. Upper Left: Classical node-link, sim- ilar to Figure 10, C, with generations progressing top-to-bottom. Lower Left: Classical node-link, with generations progressing left-to- right. Right: Indented outline style, similar to Figure 11, C.", "DPI": 100, "CaptionBB": [440, 763, 775, 829], "first_confirmed": false, "second_confirmed": false}, {"ImageID": 11, "Page": 6, "Type": "Figure", "Imagebbox": [0.08705882352941176, 0.10818181818181818, 0.4929411764705882, 0.3181818181818182], "Caption": "Figure 11: Three stages in adapting the indented outline style to dual-trees. The nodes and labels are the same as in Figure 10, C. A: Each tree is drawn in indented outline style. B: Edges are drawn in an alternative way, to clear the space between the trees. Arrows show matching nodes in both trees. C: The two trees combined.", "DPI": 100, "CaptionBB": [73, 365, 408, 431], "first_confirmed": false, "second_confirmed": false}, {"ImageID": 12, "Page": 7, "Type": "Figure", "Imagebbox": [0.5164705882352941, 0.28545454545454546, 0.9258823529411765, 0.59], "Caption": "Figure 14: A semi-transparent popup widget for expanding or col- lapsing subtrees in a single drag. The user pops up the widget over a node (A), and may now drag up or down to select whether to op- erate on the tree of ancestors or descendants. After dragging down slightly, the tree of descendants has been selected (B), and now the widget displays the number of levels the user could drag to change this tree: at most 4 levels down to expand to the full depth, or at most 2 levels up to collapse. Furthermore, the first 2 levels down are shaded in to indicate that they are already partially expanded. C and D show the subsequent feedback after dragging down almost 3 levels, or up 1 level, respectively. Releasing the mouse button com- pletes the operation. The node\u2019s tree of ancestors could similarly be expanded or collapsed in a separate invocation of the widget.", "DPI": 100, "CaptionBB": [440, 663, 775, 834], "first_confirmed": false, "second_confirmed": false}, {"ImageID": 13, "Page": 7, "Type": "Figure", "Imagebbox": [0.08588235294117647, 0.06727272727272728, 0.49411764705882355, 0.4709090909090909], "Caption": "Figure 13: Another dual-tree under 3 layouts: classical node-link top-to-bottom (Top) and left-to-right (Lower Left), and indented outline style (Lower Right). Black edges are part of the dual-tree, and nodes with bold borders lie on the axis, or path between the two roots. Additional edges from children to parents are shown in grey, to make nuclear families more apparent. For example, Rick and Susan are siblings, sharing the same parents Irene and Edgar, however Janet is a half-sibling with a different mother, as shown by the lack of a grey edge from her to Irene. Grey dots on either side of a node provide previews of the number of parents or children that the node has. Preview dots that are too numerous are collapsed into oblong shapes (e.g. under Saul and Mary), and shown in full when the cursor rolls over the node, as shown under Ethel (Top). Once over a node, the user can reveal hidden parents and children by flicking in the appropriate direction to expand the node.", "DPI": 100, "CaptionBB": [73, 532, 408, 729], "first_confirmed": false, "second_confirmed": false}]