[{"ImageID": 0, "Page": 1, "Type": "Figure", "Imagebbox": [0.6068702290076335, 0.5906468531468532, 0.8645038167938931, 0.8995348837209303], "Caption": "Fig. 1. scatterplot visualization of a book database containing 7500 items. The X-axis represents the year of publication and the Y-axis rep- resents the sale price.", "DPI": 100, "CaptionBB": [406, 991, 755, 1030], "first_confirmed": false, "second_confirmed": false}, {"ImageID": 1, "Page": 3, "Type": "Figure", "Imagebbox": [0.0532994923857868, 0.05777972027972028, 0.4484732824427481, 0.6390697674418606], "Caption": "Fig. 2. geometric-semantic ZUI: smooth transition from overview to de- empty space between objects until all navigational cues have been tail by tapping and holding the pen on the display. clipped. This problem is known as desert fog [22] and can cause se-", "DPI": 100, "CaptionBB": [42, 686, 755, 715], "first_confirmed": false, "second_confirmed": false}, {"ImageID": 2, "Page": 5, "Type": "Figure", "Imagebbox": [0.11259541984732824, 0.5640734265734266, 0.4389312977099237, 0.7674418604651163], "Caption": "Fig. 4. simulated PDA interface on a Wacom Board.", "DPI": 100, "CaptionBB": [42, 839, 296, 852], "first_confirmed": false, "second_confirmed": false}, {"ImageID": 3, "Page": 5, "Type": "Figure", "Imagebbox": [0.0532994923857868, 0.06617132867132867, 0.9593908629441624, 0.2911627906976744], "Caption": "Fig. 3. \ufb01sheye interface: a and b show a recursive distortion to remove visual clutter; in c the user taps an item to access its details; d shows a record card representation.", "DPI": 100, "CaptionBB": [42, 334, 755, 360], "first_confirmed": false, "second_confirmed": false}, {"ImageID": 4, "Page": 6, "Type": "Figure", "Imagebbox": [0.5050761421319797, 0.2669767441860465, 0.9302030456852792, 0.641860465116279], "Caption": "Fig. 5. (a) Total Task Time, (b) Visual Scan, (c) Information Access, (d) Comparison", "DPI": 100, "CaptionBB": [393, 700, 742, 726], "first_confirmed": false, "second_confirmed": false}, {"ImageID": 5, "Page": 7, "Type": "Figure", "Imagebbox": [0.15267175572519084, 0.2633741258741259, 0.40458015267175573, 0.4846511627906977], "Caption": "Fig. 6. comparing Attrakdiff PQ Scores between interface types", "DPI": 100, "CaptionBB": [42, 536, 352, 549], "first_confirmed": false, "second_confirmed": false}]