[{"ImageID": 0, "Page": 1, "Type": "Figure", "Imagebbox": [0.5211864406779662, 0.35536821350570796, 0.9517766497461929, 0.4855813953488372], "Caption": "Fig. 1: NodeTrix Representation of the largest component of the Info- Vis Co-authorship Network", "DPI": 100, "CaptionBB": [406, 537, 755, 565], "first_confirmed": false, "second_confirmed": false}, {"ImageID": 1, "Page": 4, "Type": "Figure", "Imagebbox": [0.06472081218274112, 0.0762984460638475, 0.9606598984771575, 0.19441860465116279], "Caption": "Fig. 2: Drawing links", "DPI": 100, "CaptionBB": [331, 223, 440, 237], "first_confirmed": false, "second_confirmed": false}, {"ImageID": 2, "Page": 5, "Type": "Figure", "Imagebbox": [0.5402542372881356, 0.24529069412586302, 0.940677966101695, 0.466046511627907], "Caption": "Fig. 4: The stages of an animation from a node-link diagram (1) to an adjacency matrix (5). Figure 3, sub-\ufb01gure 5 was chosen as the intermediate form through which we interpolate.", "DPI": 100, "CaptionBB": [406, 517, 755, 558], "first_confirmed": false, "second_confirmed": false}, {"ImageID": 3, "Page": 5, "Type": "Figure", "Imagebbox": [0.06991525423728813, 0.4437403065289638, 0.4830508474576271, 0.5863759654436924], "Caption": "Fig. 4: The stages of an animation from a node-link diagram (1) to an adjacency matrix (5). Figure 3, sub-\ufb01gure 5 was chosen as the intermediate form through which we interpolate.", "DPI": 100, "CaptionBB": [406, 517, 755, 558], "first_confirmed": false, "second_confirmed": false}, {"ImageID": 4, "Page": 6, "Type": "Figure", "Imagebbox": [0.5233050847457628, 0.3476162755212118, 0.9279661016949152, 0.4613953488372093], "Caption": "Fig. 6: Three collaboration patterns: (a) Shneiderman and his collab- orators, (b) Researchers at Berkeley, (c) Roth and his collaborators at CMU.", "DPI": 100, "CaptionBB": [393, 509, 742, 550], "first_confirmed": false, "second_confirmed": false}, {"ImageID": 5, "Page": 6, "Type": "Figure", "Imagebbox": [0.06598984771573604, 0.7119573607925297, 0.4533898305084746, 0.8421899189320645], "Caption": "Fig. 5: Moving a node in and out of a matrix. In the second case, red tive and simplest to understand. We plan to run further experiments lines indicate that the matrix is disconnected in two groups (upper left to quantitatively demonstrate its ef\ufb01ciency compared to state-of-the- and lower right). Ed Chi is the bridge between these two groups. art representations. NodeTrix will be released as a component of the", "DPI": 100, "CaptionBB": [30, 920, 743, 962], "first_confirmed": false, "second_confirmed": false}, {"ImageID": 6, "Page": 8, "Type": "Figure", "Imagebbox": [0.06345177664974619, 0.1507170507150103, 0.9194915254237288, 0.8], "Caption": "Fig. 7: NodeTrix visualization of the information visualization \ufb01eld. This is the largest connected component extracted from the dataset used in the Infovis\u201904 Contest available at http://www.cs.umd.edu/hcil/iv04contest/. We manually removed a couple of remaining duplicated authors. Colors on axes of matrices represent the number of citations of each author. Color intensity within the matrices represents the strength of each collaboration.", "DPI": 100, "CaptionBB": [30, 877, 743, 932], "first_confirmed": false, "second_confirmed": false}]