[{"ImageID": 0, "Page": 1, "Type": "Figure", "Imagebbox": [0.5169491525423728, 0.16470949388369796, 0.9152941176470588, 0.32181818181818184], "Caption": "Figure 1. The Information Visualization Reference Model. Source data is mapped into data tables which are visually encoded and presented in interactive views [9, 28]. Collaboration may occur at the level of data management, visualization, or analysis.", "DPI": 100, "CaptionBB": [441, 361, 769, 414], "first_confirmed": false, "second_confirmed": false}, {"ImageID": 1, "Page": 2, "Type": "Figure", "Imagebbox": [0.08588235294117647, 0.04454545454545455, 0.9152941176470588, 0.5581818181818182], "Caption": "Figure 2. Asynchronous Collaborative Visualization Systems. Clockwise from top-left, Spotfire Decision Site Posters [43], Wikimapia [50], Swivel [46], Sense.us [29], and Many Eyes [33]. These systems support varied levels of sharing, discussion, and annotation of visualized data.", "DPI": 100, "CaptionBB": [73, 621, 760, 647], "first_confirmed": false, "second_confirmed": false}, {"ImageID": 2, "Page": 3, "Type": "Figure", "Imagebbox": [0.09529411764705882, 0.6818944366005556, 0.4576271186440678, 0.8718181818181818], "Caption": "Figure 3. The Sensemaking Cycle. The diagram depicts the various phases and loops of the sensemaking process, annotated with common tasks. The image is taken from Card et al [9].", "DPI": 100, "CaptionBB": [73, 958, 394, 997], "first_confirmed": false, "second_confirmed": false}, {"ImageID": 3, "Page": 7, "Type": "Table", "Imagebbox": [0.07203389830508475, 0.058326515160293704, 0.9216101694915254, 0.3881818181818182], "Caption": "Table 1. Selected Design Considerations for Collaborative Visual Analytics. The table lists many of the individual design considerations visited in this article, providing a brief description and noting the relevant sections that discuss the issue in detail.", "DPI": 100, "CaptionBB": [73, 434, 708, 460], "first_confirmed": false, "second_confirmed": false}]