[{"ImageID": 0, "Page": 2, "Type": "Figure", "Imagebbox": [0.07442748091603053, 0.4619755244755245, 0.383587786259542, 0.6633741258741259], "Caption": "Figure 1: \"Chartjunk\u201d graph by Nigel Holmes used in Bateman et al limited effects on performance, but pictorial backgrounds generally [5]. increased response time and decreased accuracy. Adding x- and y-", "DPI": 100, "CaptionBB": [30, 736, 727, 762], "first_confirmed": false, "second_confirmed": false}, {"ImageID": 1, "Page": 3, "Type": null, "Imagebbox": [0.08396946564885496, 0.11512237762237762, 0.48091603053435117, 0.21022727272727273], "Caption": null, "DPI": null, "CaptionBB": null, "first_confirmed": false, "second_confirmed": false}, {"ImageID": 2, "Page": 6, "Type": "Table", "Imagebbox": [0.46954314720812185, 0.3207167832167832, 0.9454314720812182, 0.6586046511627907], "Caption": "Table 1: Efficiency versus difficulties recommendations in InfoVis.", "DPI": 100, "CaptionBB": [386, 744, 709, 757], "first_confirmed": false, "second_confirmed": false}, {"ImageID": 3, "Page": 6, "Type": "Table", "Imagebbox": [0.06870229007633588, 0.2633741258741259, 0.3931297709923664, 0.44519230769230766], "Caption": "Table 1: Efficiency versus difficulties recommendations in InfoVis.", "DPI": 100, "CaptionBB": [386, 744, 709, 757], "first_confirmed": false, "second_confirmed": false}]