[{"ImageID": 0, "Page": 2, "Type": "Figure", "Imagebbox": [0.09176470588235294, 0.06727272727272728, 0.9070588235294118, 0.22909090909090907], "Caption": "Figure 1: Steps of the (a) grow process; (b) optimize process; and (c) prune process.", "DPI": 100, "CaptionBB": [216, 270, 632, 283], "first_confirmed": false, "second_confirmed": false}, {"ImageID": 1, "Page": 2, "Type": "Figure", "Imagebbox": [0.5952941176470589, 0.7190909090909091, 0.8352941176470589, 0.8718181818181818], "Caption": "Figure 2: Decision tree node-link representation with annotated user tasks grow, prune and optimize.", "DPI": 100, "CaptionBB": [440, 974, 775, 1000], "first_confirmed": false, "second_confirmed": false}, {"ImageID": 2, "Page": 3, "Type": "Table", "Imagebbox": [0.08941176470588236, 0.09, 0.9117647058823528, 0.26454545454545453], "Caption": "Table 1: Requirements to support users in interactive decision tree construction tasks.", "DPI": 100, "CaptionBB": [213, 87, 634, 100], "first_confirmed": false, "second_confirmed": false}, {"ImageID": 3, "Page": 4, "Type": "Figure", "Imagebbox": [0.08588235294117647, 0.06727272727272728, 0.9129411764705884, 0.3381818181818182], "Caption": "Figure 3: Interface of the interactive decision tree construction software with according proposed decision tree visualization; Based on adapted node-link diagram. Nodes contain important decision tree components. Links are visualized as a stream of items.", "DPI": 100, "CaptionBB": [73, 387, 775, 413], "first_confirmed": false, "second_confirmed": false}, {"ImageID": 4, "Page": 5, "Type": "Figure", "Imagebbox": [0.08941176470588236, 0.74, 0.9105882352941177, 0.8218181818181818], "Caption": "Figure 5: Different data visualization methods (individual or combination) provided to users. (a) Dot plots: Over-plotting is solved by transparency. Outliers can be detected. (b) Boxplots: Showing individual class distributions. However, area of the boxplots is misleading because it does not represent quantity. For example quantities for red and blue only differ 3 items. (c) Stacked histogram: Showing individual class distributions as well as quantities. Interpretation is difficult due to discontinuities in colors. (d) Smoothed histogram: Discontinuities are prevented for easier interpretation. (e) Streamgraph: Reducing wiggles and spikes. In our opinion, the Streamgraph is best suited to see individual class distributions as well as quantities.", "DPI": 100, "CaptionBB": [73, 922, 775, 1000], "first_confirmed": false, "second_confirmed": false}, {"ImageID": 5, "Page": 5, "Type": "Figure", "Imagebbox": [0.5164705882352941, 0.06818181818181818, 0.9141176470588235, 0.10818181818181818], "Caption": "Figure 6: Ranked and sorted attributes based on gain ratio for the segment dataset from the UCI repository [1].", "DPI": 100, "CaptionBB": [440, 135, 775, 161], "first_confirmed": false, "second_confirmed": false}, {"ImageID": 6, "Page": 5, "Type": "Figure", "Imagebbox": [0.08588235294117647, 0.06818181818181818, 0.4823529411764706, 0.25727272727272726], "Caption": "Figure 4: Proposed solution to visualize a node.", "DPI": 100, "CaptionBB": [123, 299, 359, 312], "first_confirmed": false, "second_confirmed": false}, {"ImageID": 7, "Page": 6, "Type": "Figure", "Imagebbox": [0.08588235294117647, 0.7581818181818182, 0.48, 0.8836363636363637], "Caption": "Figure 8: Visual confusion matrix cells explained.", "DPI": 100, "CaptionBB": [120, 987, 362, 1000], "first_confirmed": false, "second_confirmed": false}, {"ImageID": 8, "Page": 6, "Type": "Figure", "Imagebbox": [0.08588235294117647, 0.4809090909090909, 0.4823529411764706, 0.7163636363636363], "Caption": "Figure 7: Visual confusion matrix.", "DPI": 100, "CaptionBB": [157, 805, 324, 818], "first_confirmed": false, "second_confirmed": false}, {"ImageID": 9, "Page": 7, "Type": "Figure", "Imagebbox": [0.12705882352941175, 0.3490909090909091, 0.4423529411764706, 0.8836363636363637], "Caption": "Figure 10: Tree layouts for editing and analysis processes.", "DPI": 100, "CaptionBB": [97, 990, 384, 1003], "first_confirmed": false, "second_confirmed": false}, {"ImageID": 10, "Page": 7, "Type": "Figure", "Imagebbox": [0.09058823529411765, 0.06727272727272728, 0.908235294117647, 0.22909090909090907], "Caption": "Figure 9: Additional layouts providing users more insight. (a) Default grow process layout. (b) All leaves are grouped based on majority class, enabling users to see the deepest level of a class in the tree and the number of involved leaves. (c) All leaves on same level. Enabling users to identify which nodes need to be split further, based on the class distribution bars. (d) All leaves grouped on majority class and positioned on the same level. Providing users with insight on leaf distributions.", "DPI": 100, "CaptionBB": [73, 270, 775, 322], "first_confirmed": false, "second_confirmed": false}, {"ImageID": 11, "Page": 8, "Type": "Figure", "Imagebbox": [0.5164705882352941, 0.06545454545454546, 0.9141176470588235, 0.27545454545454545], "Caption": "Figure 12: Decision tree in grow mode after automatic growing of hard to separate node (left). Decision tree in prune mode showing nodes bigger that can be pruned according to the prune set accuracy (middle). Final decision tree after pruning in analyse mode (upper right), also shown with nodes colored according to split attributes (lower right).", "DPI": 100, "CaptionBB": [440, 317, 775, 395], "first_confirmed": false, "second_confirmed": false}, {"ImageID": 12, "Page": 8, "Type": "Figure", "Imagebbox": [0.08588235294117647, 0.06636363636363636, 0.4823529411764706, 0.31272727272727274], "Caption": "Figure 11: Decision tree after 10 splits. Highlighted node is difficult to split manually. Right image shows some Streamgraphs of the al- ternative attributes that can be used to split the node. Note there is no attribute that can be used to separate the involved classes easily.", "DPI": 100, "CaptionBB": [73, 358, 408, 410], "first_confirmed": false, "second_confirmed": false}, {"ImageID": 13, "Page": 9, "Type": "Figure", "Imagebbox": [0.5164705882352941, 0.06727272727272728, 0.9141176470588235, 0.3936363636363636], "Caption": "Figure 14: Primary tumor location decision tree constructed by man- ual first-split on sex, next automatically constructed. Showing typical diagnoses for males (lower left) diagnoses for females (lower right) and diagnoses of both sexes (upper right).", "DPI": 100, "CaptionBB": [440, 450, 775, 502], "first_confirmed": false, "second_confirmed": false}, {"ImageID": 14, "Page": 9, "Type": "Figure", "Imagebbox": [0.08588235294117647, 0.06636363636363636, 0.4823529411764706, 0.3990909090909091], "Caption": "Figure 13: Primary tumor location decision tree imported from Weka, showing easy to separate classes (upper right), hard to separate classes (lower right) and misclassifications (lower left).", "DPI": 100, "CaptionBB": [73, 456, 408, 495], "first_confirmed": false, "second_confirmed": false}]