[{"ImageID": 0, "Page": 1, "Type": "Figure", "Imagebbox": [0.046610169491525424, 0.1631201514902041, 0.9631979695431472, 0.3413953488372093], "Caption": "Fig. 1. Compressed adjacency matrix of the gene regulatory network of Bacillus subtilis, which consists of approximately 700 genes and 1000 regulations [30].", "DPI": 100, "CaptionBB": [75, 381, 723, 407], "first_confirmed": false, "second_confirmed": false}, {"ImageID": 1, "Page": 2, "Type": "Figure", "Imagebbox": [0.5038071065989848, 0.5525581395348838, 0.9428934010152284, 0.8837209302325582], "Caption": "Fig. 3. Node-link diagram of the same GRN as in Fig. 1. Generated with Cytoscape [38], using a standard spring-embedder layout algo- rithm. Genes are depicted as dark gray nodes and regulations as col- ored links: green, red, orange, and blue for promotion, inhibition, both, and unspecified, respectively.", "DPI": 100, "CaptionBB": [394, 966, 744, 1031], "first_confirmed": false, "second_confirmed": false}, {"ImageID": 2, "Page": 2, "Type": "Figure", "Imagebbox": [0.1059322033898305, 0.05924418249795603, 0.4067796610169492, 0.14916666311811108], "Caption": "Fig. 3. Node-link diagram of the same GRN as in Fig. 1. Generated with Cytoscape [38], using a standard spring-embedder layout algo- rithm. Genes are depicted as dark gray nodes and regulations as col- ored links: green, red, orange, and blue for promotion, inhibition, both, and unspecified, respectively.", "DPI": 100, "CaptionBB": [394, 966, 744, 1031], "first_confirmed": false, "second_confirmed": false}, {"ImageID": 3, "Page": 3, "Type": "Figure", "Imagebbox": [0.5152284263959391, 0.062325581395348835, 0.9619289340101523, 0.5134883720930232], "Caption": "Fig. 4. Node-link diagrams of a simple network on the left and corre- sponding CAMs on the right: (a) Nodes are uniquely labelled and edges colored blue in both representations, the CAM shows edges as arcs or dots. (b) Cycles are grouped in the layout of a CAM (orange), and nodes with identical neighborhoods are stacked (red), roots are placed before edges (labelled r), hubs diagonally (labelled h), and leaves at the bot- tom (labelled l). (c) To follow a path in a CAM, one starts at a node and traces a line (red) to the right until an edge is hit, then one traces a line down until a node is hit again.", "DPI": 100, "CaptionBB": [407, 564, 757, 682], "first_confirmed": false, "second_confirmed": false}, {"ImageID": 4, "Page": 4, "Type": "Figure", "Imagebbox": [0.565989847715736, 0.23069767441860464, 0.8794416243654822, 0.3330232558139535], "Caption": "Fig. 7. Example of GI (left) and the GS (right) that is derived by grouping SCCs. The red vertices and edges are part of an SCC that is larger than a single vertex.", "DPI": 100, "CaptionBB": [394, 192, 744, 231], "first_confirmed": false, "second_confirmed": false}, {"ImageID": 5, "Page": 4, "Type": "Figure", "Imagebbox": [0.565677966101695, 0.060794570094855255, 0.8813559322033898, 0.17087208947470023], "Caption": "Fig. 7. Example of GI (left) and the GS (right) that is derived by grouping SCCs. The red vertices and edges are part of an SCC that is larger than a single vertex.", "DPI": 100, "CaptionBB": [394, 192, 744, 231], "first_confirmed": false, "second_confirmed": false}, {"ImageID": 6, "Page": 4, "Type": "Figure", "Imagebbox": [0.08050847457627118, 0.05304263211035913, 0.4067796610169492, 0.1569186011026072], "Caption": "Fig. 5. Example network (left) with its weakly connected components marked in red. In this case, the largest component is taken as G (right).", "DPI": 100, "CaptionBB": [29, 183, 379, 209], "first_confirmed": false, "second_confirmed": false}, {"ImageID": 7, "Page": 4, "Type": "Figure", "Imagebbox": [0.116751269035533, 0.20744186046511628, 0.4022842639593909, 0.3125581395348837], "Caption": "Fig. 6. Example of G (left) and the GI (right) that is derived by grouping vertices with identical neighborhoods. The vertices and edges in red are joined into a larger group.", "DPI": 100, "CaptionBB": [29, 352, 379, 391], "first_confirmed": false, "second_confirmed": false}, {"ImageID": 8, "Page": 5, "Type": "Figure", "Imagebbox": [0.6027918781725888, 0.06325581395348837, 0.8743654822335025, 0.5553488372093023], "Caption": "Fig. 10. (a) Layers of GS . (b) Blocks of GS that form a CAM. (c) Stan- dard adjacency matrix arranged according to the blocks of GS . All edge depictions are in red. Here e, f and g are leaves, c is a short root, k and a, d are long roots, b and l are short hubs, and h is a long hub.", "DPI": 100, "CaptionBB": [407, 610, 757, 662], "first_confirmed": false, "second_confirmed": false}, {"ImageID": 9, "Page": 5, "Type": "Figure", "Imagebbox": [0.07233502538071065, 0.06325581395348837, 0.47969543147208127, 0.22790697674418606], "Caption": "Fig. 9. The composition of Bi and its placement with respect to its neigh- boring blocks.", "DPI": 100, "CaptionBB": [42, 261, 392, 287], "first_confirmed": false, "second_confirmed": false}, {"ImageID": 10, "Page": 6, "Type": "Figure", "Imagebbox": [0.02918781725888325, 0.054593019707258356, 0.9533898305084746, 0.7888372093023256], "Caption": "Fig. 11. A sample of CAM configurations, applied to a section of Fig. 1: (a) Thin separating lines. (b) Non-regulations as gray dots. (c) Thick underlying lines. (d) Periodic spacing. (e) Leaves have no rearrangement clustering on neighborhood similarity. (f) Thick underlying lines are shortened. (g) Roots are treated as hubs. (h) Filtered and highlighted on two selected genes.", "DPI": 100, "CaptionBB": [29, 861, 743, 900], "first_confirmed": false, "second_confirmed": false}, {"ImageID": 11, "Page": 8, "Type": "Figure", "Imagebbox": [0.5042372881355932, 0.06544573288555293, 0.9479695431472082, 0.4], "Caption": "Fig. 13. Node-link diagram of the GRN of Escherichia coli, laid out with a spring-based method in Cytoscape as commonly used by GRN ana- lysts.", "DPI": 100, "CaptionBB": [394, 452, 744, 491], "first_confirmed": false, "second_confirmed": false}, {"ImageID": 12, "Page": 8, "Type": "Figure", "Imagebbox": [0.07838983050847458, 0.05304263211035913, 0.4279661016949153, 0.9429651127305142], "Caption": "Fig. 12. Rotated CAM of the GRN of bacterium Escherichia coli.", "DPI": 100, "CaptionBB": [29, 1025, 344, 1038], "first_confirmed": false, "second_confirmed": false}, {"ImageID": 13, "Page": 9, "Type": "Figure", "Imagebbox": [0.05583756345177665, 0.06325581395348837, 0.5084745762711864, 0.15846898869950643], "Caption": "The presence of cycles is clearly lost in large node-link diagrams, Fig. 14. Illustrations of GRN motifs, generalized of regulation types. where the nodes of a cycle can have large distance between them, and Gray areas represent the remainder of a network.", "DPI": 100, "CaptionBB": [42, 169, 756, 204], "first_confirmed": false, "second_confirmed": false}]