[{"ImageID": 0, "Page": 1, "Type": null, "Imagebbox": [0.08610271903323263, 0.15337763012181616, 0.9033232628398792, 0.41362126245847175], "Caption": null, "DPI": null, "CaptionBB": null, "first_confirmed": false, "second_confirmed": false}, {"ImageID": 1, "Page": 4, "Type": null, "Imagebbox": [0.0891238670694864, 0.055924695459579184, 0.45770392749244715, 0.18438538205980065], "Caption": null, "DPI": null, "CaptionBB": null, "first_confirmed": false, "second_confirmed": false}, {"ImageID": 2, "Page": 4, "Type": null, "Imagebbox": [0.5785498489425982, 0.0592469545957918, 0.9018126888217523, 0.1212624584717608], "Caption": null, "DPI": null, "CaptionBB": null, "first_confirmed": false, "second_confirmed": false}, {"ImageID": 3, "Page": 5, "Type": null, "Imagebbox": [0.05740181268882175, 0.05813953488372093, 0.4622356495468278, 0.30398671096345514], "Caption": null, "DPI": null, "CaptionBB": null, "first_confirmed": false, "second_confirmed": false}, {"ImageID": 4, "Page": 6, "Type": null, "Imagebbox": [0.08157099697885196, 0.05813953488372093, 0.4486404833836858, 0.5365448504983389], "Caption": null, "DPI": null, "CaptionBB": null, "first_confirmed": false, "second_confirmed": false}, {"ImageID": 5, "Page": 6, "Type": null, "Imagebbox": [0.620845921450151, 0.06035437430786268, 0.8610271903323263, 0.20985603543743075], "Caption": null, "DPI": null, "CaptionBB": null, "first_confirmed": false, "second_confirmed": false}, {"ImageID": 6, "Page": 7, "Type": null, "Imagebbox": [0.0891238670694864, 0.06035437430786268, 0.43051359516616317, 0.2596899224806202], "Caption": null, "DPI": null, "CaptionBB": null, "first_confirmed": false, "second_confirmed": false}, {"ImageID": 7, "Page": 8, "Type": null, "Imagebbox": [0.12084592145015106, 0.05703211517165006, 0.8927492447129909, 0.2131782945736434], "Caption": null, "DPI": null, "CaptionBB": null, "first_confirmed": false, "second_confirmed": false}, {"ImageID": 8, "Page": 8, "Type": null, "Imagebbox": [0.06797583081570997, 0.3117386489479513, 0.9486404833836858, 0.39811738648947953], "Caption": null, "DPI": null, "CaptionBB": null, "first_confirmed": false, "second_confirmed": false}, {"ImageID": 9, "Page": 9, "Type": null, "Imagebbox": [0.05740181268882175, 0.05703211517165006, 0.918429003021148, 0.1611295681063123], "Caption": null, "DPI": null, "CaptionBB": null, "first_confirmed": false, "second_confirmed": false}]