[{"ImageID": 0, "Page": 1, "Type": "Table", "Imagebbox": [0.13771186440677965, 0.484593837535014, 0.4152542372881356, 0.5197092987770258], "Caption": "Table 1: Three hypothetical candidates in political elections", "DPI": 100, "CaptionBB": [61, 499, 370, 514], "first_confirmed": false, "second_confirmed": false}, {"ImageID": 1, "Page": 4, "Type": "Figure", "Imagebbox": [0.059322033898305086, 0.051492244513459906, 0.461864406779661, 0.2638953452886537], "Caption": "Table and scatterplot tests. After carrying out the task, partici- Fig. 1: Examples of experimental stimuli for the table (a,b) and the pants were subjected to two screening tests: a numerical table test, scatterplot (c,d) conditions. The left decision task (a,c) has no decoy, and a scatterplot test, irrespective of the condition they saw. Both while the right decision task (b,d) has a decoy on B.", "DPI": 100, "CaptionBB": [28, 284, 743, 334], "first_confirmed": false, "second_confirmed": false}, {"ImageID": 2, "Page": 5, "Type": "Figure", "Imagebbox": [0.06991525423728813, 0.2638953452886537, 0.4809322033898305, 0.40896358543417366], "Caption": "Fig. 2: Participant demographics for both experiments.", "DPI": 100, "CaptionBB": [73, 448, 357, 463], "first_confirmed": false, "second_confirmed": false}, {"ImageID": 3, "Page": 5, "Type": "Figure", "Imagebbox": [0.5466101694915254, 0.05304263211035913, 0.9322033898305084, 0.19234360410831003], "Caption": "Fig. 3: Proportions of participant choices in both experiments.", "DPI": 100, "CaptionBB": [419, 211, 741, 226], "first_confirmed": false, "second_confirmed": false}, {"ImageID": 4, "Page": 5, "Type": "Figure", "Imagebbox": [0.5357142857142857, 0.2222222222222222, 0.9489795918367347, 0.4061624649859944], "Caption": "Fig. 4: Point estimates and 95% confidence intervals for the attrac- tion effects in Malkoc et al. [33], and in our two experiments.", "DPI": 100, "CaptionBB": [405, 446, 755, 475], "first_confirmed": false, "second_confirmed": false}, {"ImageID": 5, "Page": 6, "Type": "Figure", "Imagebbox": [0.5, 0.4964534848235374, 0.9533898305084746, 0.5714285714285714], "Caption": "Fig. 6: A baseline decision task T0 and two possible test decision tasks: T A , where A is the target, and TB , where B is the target.", "DPI": 100, "CaptionBB": [392, 622, 742, 653], "first_confirmed": false, "second_confirmed": false}, {"ImageID": 6, "Page": 6, "Type": "Figure", "Imagebbox": [0.08050847457627118, 0.051492244513459906, 0.4343220338983051, 0.14285714285714285], "Caption": "Fig. 5: Self-reported confidence and familiarity in both experiments.", "DPI": 100, "CaptionBB": [28, 158, 378, 173], "first_confirmed": false, "second_confirmed": false}, {"ImageID": 7, "Page": 7, "Type": "Figure", "Imagebbox": [0.5169491525423728, 0.05304263211035913, 0.9639830508474576, 0.20915032679738566], "Caption": "Fig. 7: Experimental stimuli for the two matched decision tasks AC and C A (black-and-white background images), and explanatory an- notations (box overlays). See Section 4.2 for the full details.", "DPI": 100, "CaptionBB": [405, 224, 755, 267], "first_confirmed": false, "second_confirmed": false}, {"ImageID": 8, "Page": 7, "Type": "Table", "Imagebbox": [0.1292372881355932, 0.5305620119553204, 0.423728813559322, 0.5662209266840026], "Caption": "Table 2: The non-dominated alternatives used in our tasks.", "DPI": 100, "CaptionBB": [63, 552, 368, 567], "first_confirmed": false, "second_confirmed": false}, {"ImageID": 9, "Page": 8, "Type": "Figure", "Imagebbox": [0.5211864406779662, 0.4158333297847777, 0.923728813559322, 0.5340802987861811], "Caption": "Fig. 8: Contingency tables showing choice pairs for all matched tasks", "DPI": 100, "CaptionBB": [393, 574, 743, 589], "first_confirmed": false, "second_confirmed": false}]