[{"ImageID": 0, "Page": 1, "Type": "Figure", "Imagebbox": [0.125, 0.14426622418879056, 0.8771186440677966, 0.38545454545454544], "Caption": "2GMMOTM 2GMMOTM 2GMMOTM )69,_;9>Z\u72ea \u0150\u01b5\u0176\u0190 \u0189\u015d\u0189\u011e\u016f\u015d\u0176\u011e \u019a\u018c\u01b5\u0190\u019a\u011e\u011a &:KJ)X[`\u72e6=. \u72e3\u72e4 \u72e2\u72e3 \u72e4\u72e2\u72e3\u72e7 \u72e2\u72e5 \u72e4\u72ea \u72e2\u72e3 :KJ)X[` &:KJ)X[` :KJ)X[`\u72e4\u72e2\u72e3\u72e8 NZZVY Z IU Figure 1: Top-level idea clusters and the\u011a\u011e\u0102\u016f \u0176\u018c\u0102 \u019a\u011e\u011a\u0110\u018c\u01b5\u01cc\u03ee\u03ec\u03ed\u03f2flows corresponding of the Congress \u039bEz^\u03f0 \u018c\u01b5\u01cc data: (a) an overview of ideas; (b) lead-lag relationships over time; S_UO=\u72e6\u72e29V+ :X[Y:+* :KJ)X[`8UIQY NZZVY Z IU \u01c0\u017d\u019a\u011e :KJ)X[` &:KJ)X[` :KJ)X[`\u72e4\u72e2\u72e3\u72e8 NZZVY Z IU \u039bd\u011e\u011a \u018c\u01b5\u01cc\u03f0t, ?7IL`*(+\u72e4Y \u0189\u0169\u0176\u011e\u019a \u0110\u018c\u01b5\u01cc\u0110\u018c\u011e\u01c1 \u03ee\u0102 \u019a\u0110\u017d\u019a S_UO=\u72e6\u72e29V+ :X[Y:+* :KJ)X[`8UIQY NZZVY &:KJ)X[`\u72e6=. \u72e3\u72e4 \u72e2\u72e3 \u72e4\u72e2\u72e3\u72e7 \u72e2\u72e5 \u72e4\u72eb \u72e3\u72e6 Z IU (c) information panel. Z8+G<.LS\u72e9+ &:KJ)X[`\u72e6=. \u72e3\u72e4 \u72e2\u72e3 \u72e4\u72e2\u72e3\u72e7 \u72e2\u72e5 \u72e4\u72ea \u72e6\u72e7 :KJ)X[` &:KJ)X[` :KJ)X[`\u72e4\u72e2\u72e3\u72e8 NZZVY Z IU", "DPI": 100, "CaptionBB": [73, 425, 776, 456], "first_confirmed": false, "second_confirmed": false}, {"ImageID": 1, "Page": 4, "Type": "Figure", "Imagebbox": [0.10588235294117647, 0.06909090909090909, 0.8894117647058823, 0.19636363636363635], "Caption": "Figure 2: System overview.", "DPI": 100, "CaptionBB": [356, 216, 491, 229], "first_confirmed": false, "second_confirmed": false}, {"ImageID": 2, "Page": 4, "Type": "Figure", "Imagebbox": [0.5188235294117647, 0.7354545454545455, 0.9329411764705883, 0.8863636363636364], "Caption": "Figure 3: Basic idea of the idea flow tracking algorithm: (a) aug- mented word graph; (b) lead-lag relationships between ideas.", "DPI": 100, "CaptionBB": [440, 974, 777, 1000], "first_confirmed": false, "second_confirmed": false}, {"ImageID": 3, "Page": 5, "Type": "Figure", "Imagebbox": [0.11647058823529412, 0.06727272727272728, 0.44941176470588234, 0.1690909090909091], "Caption": "Figure 4: Three-level random-walk-based model for temporal corre- lation calculation.", "DPI": 100, "CaptionBB": [73, 187, 410, 213], "first_confirmed": false, "second_confirmed": false}, {"ImageID": 4, "Page": 5, "Type": "Figure", "Imagebbox": [0.7309160305343512, 0.37545454545454543, 0.8858823529411765, 0.41818181818181815], "Caption": "Figure 5: Global lead-lag glyph.", "DPI": 100, "CaptionBB": [615, 461, 772, 474], "first_confirmed": false, "second_confirmed": false}, {"ImageID": 5, "Page": 6, "Type": "Figure", "Imagebbox": [0.09529411764705882, 0.06727272727272728, 0.9070588235294118, 0.19090909090909092], "Caption": "Figure 6: Correlated-clustering-based flow map layout: (a) local lead-lag relationships formulated as a DAG; (b) DAG after applying ambiguity- aware filtering; (c) flow maps generated by clustering target nodes of different source nodes independently; (d) flow maps generated by using correlated clustering; (e) final flow map visualization after smoothing.", "DPI": 100, "CaptionBB": [73, 211, 777, 250], "first_confirmed": false, "second_confirmed": false}, {"ImageID": 6, "Page": 7, "Type": "Table", "Imagebbox": [0.5411764705882353, 0.86, 0.8870588235294118, 0.9109090909090909], "Caption": "Table 1: Comparison of the model accuracy of different methods.", "DPI": 100, "CaptionBB": [448, 931, 767, 944], "first_confirmed": false, "second_confirmed": false}, {"ImageID": 7, "Page": 8, "Type": "Figure", "Imagebbox": [0.5164705882352941, 0.06818181818181818, 0.9329411764705883, 0.19454545454545455], "Caption": "Figure 8: Flow of sentiment towards Sierra Leone related ideas.", "DPI": 100, "CaptionBB": [451, 213, 764, 226], "first_confirmed": false, "second_confirmed": false}, {"ImageID": 8, "Page": 8, "Type": "Figure", "Imagebbox": [0.08588235294117647, 0.06818181818181818, 0.4858823529411765, 0.23363636363636364], "Caption": "Figure 7: Holiday related ideas.", "DPI": 100, "CaptionBB": [163, 266, 318, 279], "first_confirmed": false, "second_confirmed": false}, {"ImageID": 9, "Page": 9, "Type": "Figure", "Imagebbox": [0.08588235294117647, 0.06727272727272728, 0.5023529411764706, 0.3372727272727273], "Caption": "Figure 9: Idea flows within and across multiple continents.", "DPI": 100, "CaptionBB": [98, 370, 383, 383], "first_confirmed": false, "second_confirmed": false}]