[{"ImageID": 0, "Page": 2, "Type": "Figure", "Imagebbox": [0.13529411764705881, 0.72, 0.4152941176470588, 0.81], "Caption": "Figure 1. The conventional visualization.", "DPI": 100, "CaptionBB": [99, 909, 367, 924], "first_confirmed": false, "second_confirmed": false}, {"ImageID": 1, "Page": 3, "Type": "Figure", "Imagebbox": [0.1588235294117647, 0.025454545454545455, 0.8152941176470588, 0.4490909090909091], "Caption": "Figure 2. The lifting-up operation: In this example, as the user lifts the cell H14 up successively, the cell H13 on which H14 depends follows, and so on.", "DPI": 100, "CaptionBB": [84, 510, 740, 541], "first_confirmed": false, "second_confirmed": false}, {"ImageID": 2, "Page": 4, "Type": "Figure", "Imagebbox": [0.10235294117647059, 0.026363636363636363, 0.44941176470588234, 0.18636363636363637], "Caption": "Figure 3. Users can investigate dependencies between even distant cells.", "DPI": 100, "CaptionBB": [84, 221, 381, 252], "first_confirmed": false, "second_confirmed": false}]